{"took":2,"timed_out":false,"_shards":{"total":1,"successful":1,"skipped":0,"failed":0},"hits":{"total":1,"max_score":1.0,"hits":[{"_index":".kibana","_type":"doc","_id":"dashboard:16767e00-496c-11e8-a3a4-57df2c598fcb","_score":1.0,"_source":{"type":"dashboard","updated_at":"2019-09-09T14:13:17.444Z","dashboard":{"title":"kaapana","hits":0,"description":"","panelsJSON":"[{\"panelIndex\":\"5\",\"gridData\":{\"x\":14,\"y\":94,\"w\":16,\"h\":19,\"i\":\"5\"},\"id\":\"1399b0e0-1b81-11e7-bd5d-db91c77cdfc6\",\"title\":\"Series Description\",\"type\":\"visualization\",\"version\":\"6.3.0\"},{\"panelIndex\":\"6\",\"gridData\":{\"x\":30,\"y\":94,\"w\":18,\"h\":19,\"i\":\"6\"},\"embeddableConfig\":{\"spy\":null,\"vis\":{\"params\":{\"sort\":{\"columnIndex\":null,\"direction\":null}}}},\"id\":\"51208de0-4a05-11e8-a3a4-57df2c598fcb\",\"title\":\"Procedure Description\",\"type\":\"visualization\",\"version\":\"6.3.0\"},{\"panelIndex\":\"8\",\"gridData\":{\"x\":21,\"y\":113,\"w\":27,\"h\":24,\"i\":\"8\"},\"embeddableConfig\":{\"vis\":{\"colors\":{\"CT\":\"#64B0C8\",\"MR\":\"#2F575E\",\"NM\":\"#F2C96D\",\"SR\":\"#AEA2E0\",\"Unique count of 0020000D StudyInstanceUID_keyword.keyword\":\"#7EB26D\"}}},\"id\":\"43615780-4a1d-11e8-a3a4-57df2c598fcb\",\"type\":\"visualization\",\"version\":\"6.3.0\"},{\"panelIndex\":\"10\",\"gridData\":{\"x\":0,\"y\":27,\"w\":23,\"h\":20,\"i\":\"10\"},\"embeddableConfig\":{\"vis\":{\"colors\":{\"F\":\"#BF1B00\",\"M\":\"#0A50A1\",\"Other/Missing\":\"#629E51\"}}},\"id\":\"bcf33620-4f6f-11e8-8bbc-a37cd7e32d52\",\"title\":\"Patient Age by Sex\",\"type\":\"visualization\",\"version\":\"6.3.0\"},{\"panelIndex\":\"12\",\"gridData\":{\"x\":0,\"y\":113,\"w\":21,\"h\":24,\"i\":\"12\"},\"id\":\"84289ef0-4f76-11e8-8bbc-a37cd7e32d52\",\"title\":\"Modality Usage\",\"type\":\"visualization\",\"version\":\"6.3.0\"},{\"panelIndex\":\"16\",\"gridData\":{\"x\":13,\"y\":8,\"w\":15,\"h\":19,\"i\":\"16\"},\"embeddableConfig\":{\"vis\":{\"colors\":{\"CT\":\"#64B0C8\",\"MR\":\"#2F575E\",\"NM\":\"#F4D598\",\"SR\":\"#AEA2E0\"},\"legendOpen\":false}},\"id\":\"efb0b700-2638-11e8-87c0-6910c12ed7d4\",\"title\":\"Modality Donut\",\"type\":\"visualization\",\"version\":\"6.3.0\"},{\"panelIndex\":\"18\",\"gridData\":{\"x\":0,\"y\":94,\"w\":14,\"h\":19,\"i\":\"18\"},\"id\":\"45f1ca00-536b-11e8-ba0e-67fd72e50763\",\"title\":\"Body Part Examined\",\"type\":\"visualization\",\"version\":\"6.3.0\"},{\"panelIndex\":\"19\",\"gridData\":{\"x\":36,\"y\":161,\"w\":12,\"h\":22,\"i\":\"19\"},\"id\":\"bf120c70-536a-11e8-ba0e-67fd72e50763\",\"type\":\"visualization\",\"version\":\"6.3.0\"},{\"panelIndex\":\"20\",\"gridData\":{\"x\":0,\"y\":137,\"w\":21,\"h\":24,\"i\":\"20\"},\"id\":\"40168700-5399-11e8-ba0e-67fd72e50763\",\"title\":\"Manufacturer and Device\",\"type\":\"visualization\",\"version\":\"6.3.0\"},{\"panelIndex\":\"21\",\"gridData\":{\"x\":0,\"y\":0,\"w\":48,\"h\":8,\"i\":\"21\"},\"embeddableConfig\":{},\"id\":\"9823e6d0-b1a5-11e8-8c39-af1d5340b08a\",\"type\":\"visualization\",\"version\":\"6.3.0\"},{\"panelIndex\":\"25\",\"gridData\":{\"x\":23,\"y\":27,\"w\":25,\"h\":20,\"i\":\"25\"},\"embeddableConfig\":{},\"id\":\"5e382340-4f77-11e8-8bbc-a37cd7e32d52\",\"type\":\"visualization\",\"version\":\"6.3.0\"},{\"panelIndex\":\"26\",\"gridData\":{\"x\":28,\"y\":8,\"w\":20,\"h\":7,\"i\":\"26\"},\"embeddableConfig\":{},\"id\":\"6ec8cc60-5381-11e8-ba0e-67fd72e50763\",\"title\":\"Patient Sex Numbers\",\"type\":\"visualization\",\"version\":\"6.3.0\"},{\"panelIndex\":\"27\",\"gridData\":{\"x\":28,\"y\":15,\"w\":20,\"h\":12,\"i\":\"27\"},\"embeddableConfig\":{\"vis\":{\"legendOpen\":false}},\"id\":\"a84a8150-b811-11e8-9844-fbac0473ab5c\",\"title\":\"Gender Donut\",\"type\":\"visualization\",\"version\":\"6.3.0\"},{\"panelIndex\":\"28\",\"gridData\":{\"x\":0,\"y\":47,\"w\":48,\"h\":17,\"i\":\"28\"},\"embeddableConfig\":{},\"id\":\"9093c010-4955-11e8-a3a4-57df2c598fcb\",\"type\":\"visualization\",\"version\":\"6.3.0\"},{\"panelIndex\":\"29\",\"gridData\":{\"x\":0,\"y\":64,\"w\":48,\"h\":15,\"i\":\"29\"},\"embeddableConfig\":{},\"id\":\"ba5f3050-b813-11e8-9844-fbac0473ab5c\",\"title\":\"Patient Weight over Age by Sex\",\"type\":\"visualization\",\"version\":\"6.3.0\"},{\"panelIndex\":\"30\",\"gridData\":{\"x\":0,\"y\":79,\"w\":48,\"h\":15,\"i\":\"30\"},\"embeddableConfig\":{},\"id\":\"2659cd00-b81a-11e8-9844-fbac0473ab5c\",\"title\":\"Patient Weight over Size by Sex\",\"type\":\"visualization\",\"version\":\"6.3.0\"},{\"panelIndex\":\"32\",\"gridData\":{\"x\":21,\"y\":137,\"w\":27,\"h\":24,\"i\":\"32\"},\"embeddableConfig\":{},\"id\":\"17a510e0-b823-11e8-9844-fbac0473ab5c\",\"title\":\"Manufacturer Graph\",\"type\":\"visualization\",\"version\":\"6.3.0\"},{\"panelIndex\":\"34\",\"gridData\":{\"x\":0,\"y\":161,\"w\":36,\"h\":22,\"i\":\"34\"},\"embeddableConfig\":{},\"id\":\"ca4bcb00-b81c-11e8-9844-fbac0473ab5c\",\"type\":\"visualization\",\"version\":\"6.3.0\"},{\"panelIndex\":\"35\",\"gridData\":{\"x\":0,\"y\":183,\"w\":48,\"h\":11,\"i\":\"35\"},\"embeddableConfig\":{},\"id\":\"9f37efe0-3b4b-11e9-ba5b-d5ff5fba9a31\",\"title\":\"Radiomics Kidney\",\"type\":\"visualization\",\"version\":\"6.3.0\"},{\"panelIndex\":\"36\",\"gridData\":{\"x\":0,\"y\":194,\"w\":48,\"h\":11,\"i\":\"36\"},\"embeddableConfig\":{},\"id\":\"b7993d50-3b4b-11e9-ba5b-d5ff5fba9a31\",\"title\":\"Radiomics Liver\",\"type\":\"visualization\",\"version\":\"6.3.0\"},{\"panelIndex\":\"37\",\"gridData\":{\"x\":0,\"y\":205,\"w\":48,\"h\":10,\"i\":\"37\"},\"embeddableConfig\":{},\"id\":\"c2da4060-3b4b-11e9-ba5b-d5ff5fba9a31\",\"title\":\"Radiomics Spleen\",\"type\":\"visualization\",\"version\":\"6.3.0\"},{\"panelIndex\":\"38\",\"gridData\":{\"x\":0,\"y\":8,\"w\":13,\"h\":19,\"i\":\"38\"},\"embeddableConfig\":{},\"id\":\"01e08e70-4017-11e9-acb6-29d3d979e91d\",\"title\":\"Datasets\",\"type\":\"visualization\",\"version\":\"6.3.0\"},{\"panelIndex\":\"39\",\"gridData\":{\"x\":0,\"y\":215,\"w\":48,\"h\":12,\"i\":\"39\"},\"version\":\"6.3.0\",\"type\":\"visualization\",\"id\":\"19a84c80-be72-11e9-939e-81bcce751f23\",\"embeddableConfig\":{}}]","optionsJSON":"{\"darkTheme\":false,\"hidePanelTitles\":false,\"useMargins\":true}","version":1,"timeRestore":true,"timeTo":"Thu Oct 15 2020 12:49:49 GMT+0200","timeFrom":"Thu Oct 15 1970 12:49:49 GMT+0100","refreshInterval":{"display":"Off","pause":false,"section":0,"value":0},"kibanaSavedObjectMeta":{"searchSourceJSON":"{\"query\":{\"language\":\"lucene\",\"query\":\"\"},\"filter\":[],\"highlightAll\":true,\"version\":true}"}}}}]}}